[
  {"admin_question1":"(circle 40 \"solid\" \"red\")","admin_question2":"(circle 40 \"solid\" \"yellow\")","admin_question3":"(circle 40 \"solid\" \"blue\")","admin_question4":"(circle 40 \"solid\" \"green\")","admin_answer1":"(circle 40 \"solid\" \"green\")","admin_answer2":"(circle 40 \"solid\" \"orange\")","admin_answer3":"(circle 40 \"solid\" \"purple\")","admin_answer4":"(circle 40 \"solid\" \"yellow\")","correct_answer":"D"},
{"admin_question1":"(circle 40 \"solid\" \"red\")","admin_question2":"(circle 20 \"solid\" \"red\")","admin_question3":"(circle 10 \"solid\" \"red\")","admin_question4":"(circle 80 \"solid\" \"red\")","admin_answer1":"(circle 80 \"solid\" \"red\")","admin_answer2":"(circle 30 \"solid\" \"red\")","admin_answer3":"(circle 40 \"solid\" \"red\")","admin_answer4":"(circle 15 \"solid\" \"red\")","correct_answer":"C"},
{"admin_question1":"(circle 40 \"solid\" \"red\")","admin_question2":"(circle 40 \"outline\" \"red\")","admin_question3":"(circle 20 \"outline\" \"red\")","admin_question4":"(circle 20 \"solid\" \"red\")","admin_answer1":"(circle 20 \"solid\" \"red\")","admin_answer2":"(circle 60 \"solid\" \"red\")","admin_answer3":"(circle 25 \"outline\" \"red\")","admin_answer4":"(circle 80 \"outline\" \"red\")","correct_answer":"C"},
{"admin_question1":"(circle 50 \"solid\" \"red\")","admin_question2":"(square 50 \"solid\" \"red\")","admin_question3":"(star 50 \"solid\" \"red\")","admin_question4":"(triangle 50 \"solid\" \"red\")","admin_answer1":"(triangle 50 \"solid\" \"red\")","admin_answer2":"(square 50 \"solid\" \"red\")","admin_answer3":"(star 50 \"solid\" \"red\")","admin_answer4":"(octagon 50 \"solid\" \"red\")","correct_answer":"A"},
{"admin_question1":"(circle 25 \"solid\" \"yellow\")","admin_question2":"(triangle 50 \"solid\" \"orange\")","admin_question3":"(octagon 25 \"outline\" \"green\")","admin_question4":"(pentagon 50 \"outline\" \"blue\")","admin_answer1":"(pentagon 50 \"outline\" \"blue\")","admin_answer2":"(circle 25 \"solid\" \"red\")","admin_answer3":"(star 50 \"solid\" \"blue\")","admin_answer4":"(circle 50 \"solid\" \"yellow\")","correct_answer":"B"},
{"admin_question1":"(circle (+ 3 3) \"solid\" \"blue\")","admin_question2":"(circle (+ 20 20) \"solid\" \"blue\")","admin_question3":"(circle (+ 20 10) \"solid\" \"blue\")","admin_question4":"(circle (+ 10 15) \"solid\" \"blue\")","admin_answer1":"(circle (+ 10 15) \"solid\" \"blue\")","admin_answer2":"(circle 40 \"solid\" \"blue\")","admin_answer3":"(circle 10 \"solid\" \"blue\")","admin_answer4":"(circle 60 \"solid\" \"blue\")","correct_answer":"A"},
{"admin_question1":"(square (- 10 0) \"solid\" \"green\")","admin_question2":"(square (- 30 2) \"solid\" \"green\")","admin_question3":"(square (- 70 10) \"solid\" \"green\")","admin_question4":"(square (- 200 100) \"solid\" \"green\")","admin_answer1":"(square (- 200 100) \"solid\" \"green\")","admin_answer2":"(square 50 \"solid\" \"green\")","admin_answer3":"(square 30 \"solid\" \"green\")","admin_answer4":"(square 20 \"solid\" \"green\")","correct_answer":"A"},
{"admin_question1":"(beside (square 30 \"solid\" \"green\") (square 30 \"solid\" \"blue\"))","admin_question2":"(beside (square 30 \"solid\" \"yellow\") (square 30 \"solid\" \"orange\"))","admin_question3":"(beside (square 30 \"solid\" \"blue\") (square 30 \"solid\" \"green\"))","admin_question4":"(beside (square 30 \"solid\" \"red\") (square 30 \"solid\" \"purple\"))","admin_answer1":"(beside (square 30 \"solid\" \"red\") (square 30 \"solid\" \"purple\"))","admin_answer2":"(beside (square 40 \"solid\" \"red\") (square 40 \"solid\" \"green\"))","admin_answer3":"(beside (square 30 \"solid\" \"purple\") (square 30 \"solid\" \"red\"))","admin_answer4":"(beside (square 30 \"solid\" \"orange\") (square 30 \"solid\" \"purple\"))","correct_answer":"B"},
{"admin_question1":"(above (square 80 \"solid\" \"red\") (circle 40 \"solid\" \"red\"))","admin_question2":"(above (square 80 \"solid\" \"green\") (circle 40 \"solid\" \"blue\"))","admin_question3":"(above (circle 40 \"solid\" \"blue\") (square 80 \"solid\" \"green\"))","admin_question4":"(above (pentagon 40 \"solid\" \"purple\") (star 40 \"solid\" \"orange\"))","admin_answer1":"(above (pentagon 40 \"solid\" \"purple\") (star 40 \"solid\" \"orange\"))","admin_answer2":"(above (star 40 \"solid\" \"orange\") (star 40 \"solid\" \"purple\"))","admin_answer3":"(above (square 40 \"solid\" \"purple\") (circle 20 \"solid\" \"orange\"))","admin_answer4":"(above (star 40 \"solid\" \"orange\") (pentagon 40 \"solid\" \"purple\"))","correct_answer":"C"},
  {"admin_question1":"(square (- 40 2) \"solid\" \"green\")","admin_question2":"(square (* 40 2) \"solid\" \"green\")","admin_question3":"(square (+ 40 2) \"solid\" \"green\")","admin_question4":"(square (/ 40 2) \"solid\" \"green\")","admin_answer1":"(square (/ 40 2) \"solid\" \"green\")","admin_answer2":"(square (* 40 2) \"solid\" \"green\")","admin_answer3":"(square 40 \"solid\" \"green\")","admin_answer4":"(square 5 \"solid\" \"green\")","correct_answer":"C"}
]
